rtl/Flag_CrossDomain.v
module Flag_CrossDomain(
	input wire clkA,
	input wire FlagIn,
	input wire clkB,
	output wire FlagOut
);

	reg FlagToggle;
	initial FlagToggle = 0;
	always @(posedge clkA) FlagToggle <= FlagToggle ^ FlagIn;

	reg [2:0] SyncA;
	initial SyncA = 0;
	always @(posedge clkB) SyncA <= {SyncA[1:0], FlagToggle};
	
	assign FlagOut = SyncA[2] ^ SyncA[1];

endmodule

bentch/Flag_CrossDomain_test.v
`include "../rtl/Flag_CrossDomain.v"
`timescale 1ns/100ps

module Flag_CrossDomain_test();

	reg clkA;
	reg clkB;
	reg FlagIn;
	wire FlagOut;

	
	initial clkA = 0;
	initial clkB = 0;
	initial FlagIn = 0;

	always #10 clkA = !clkA;
	always #20 clkB = !clkB;


	Flag_CrossDomain i_fc(
		.clkA(clkA),
		.clkB(clkB),
		.FlagIn(FlagIn),
		.FlagOut(FlagOut)
	);

	initial begin
		#100 FlagIn = 1;
		#40 FlagIn = 0;
		#300 $finish;
	end

	initial begin
		//$monitor("%d, %b, %b, %b, %b, %b",$stime,clkA, clkB, FlagIn,FlagOut,my_Flag_CrossDomain.FlagToggle);
		$dumpfile("Flag_CrossDomain_test.vcd");
		//$dumpvars(0,Flag_CrossDomain_test);
		$dumpvars;
	end
endmodule

bentch/Flag_CrossDomain_test.vcd
$date
	Tue Nov  6 14:18:15 2018
$end
$version
	Icarus Verilog
$end
$timescale
	100ps
$end
$scope module Flag_CrossDomain_test $end
$var wire 1 ! FlagOut $end
$var reg 1 " FlagIn $end
$var reg 1 # clkA $end
$var reg 1 $ clkB $end
$scope module i_fc $end
$var wire 1 % FlagIn $end
$var wire 1 ! FlagOut $end
$var wire 1 & clkA $end
$var wire 1 ' clkB $end
$var reg 1 ( FlagToggle $end
$var reg 3 ) SyncA [2:0] $end
$upscope $end
$upscope $end
$enddefinitions $end
#0
$dumpvars
b0 )
0(
0'
0&
0%
0$
0#
0"
0!
$end
#100
1$
1'
#200
0$
0'
1#
1&
#300
1$
1'
#400
0$
0'
0#
0&
#500
1$
1'
#600
0$
0'
1#
1&
#700
1$
1'
#800
0$
0'
0#
0&
#900
1$
1'
#1000
0$
0'
1#
1&
#1100
1$
1'
#1200
1"
1%
0$
0'
0#
0&
#1300
1$
1'
#1400
1(
0$
0'
1#
1&
#1500
b1 )
1$
1'
#1600
0"
0%
0$
0'
0#
0&
#1700
1!
b11 )
1$
1'
#1800
0$
0'
1#
1&
#1900
0!
b111 )
1$
1'
#2000
0$
0'
0#
0&
#2100
1$
1'
#2200
0$
0'
1#
1&
#2300
1$
1'
#2400
0$
0'
0#
0&
#2500
1$
1'
#2600
0$
0'
1#
1&
#2700
1$
1'
#2800
1"
1%
0$
0'
0#
0&
#2900
1$
1'
#3000
0(
0$
0'
1#
1&
#3100
b110 )
1$
1'
#3200
0"
0%
0$
0'
0#
0&
#3300
1!
b100 )
1$
1'
#3400
0$
0'
1#
1&
#3500
0!
b0 )
1$
1'
