rtl/TaskAck_CrossDomain.v
`timescale 1ns/100ps

// clkA should be slower than clkB

module TaskAck_CrossDomain(
	input wire clkA,
	input wire TaskA_start,
	output wire TaskA_busy,
	output wire TaskA_done,

	input wire clkB,
	output wire TaskB_start,
	output wire TaskB_busy,
	input wire TaskB_done
);

	reg FlagToggleA;
	reg FlagToggleB;
	reg Busyhold;
	reg [2:0] SyncA;
	reg [2:0] SyncB;
	initial FlagToggleA = 0;
	initial FlagToggleB = 0;
	initial Busyhold = 0;
	initial SyncA = 0;
	initial SyncB = 0;

	always @(posedge clkA) FlagToggleA <= FlagToggleA ^ (TaskA_start&~TaskA_busy);
	always @(posedge clkB) SyncA <= {SyncA[1:0], FlagToggleA};
	assign TaskB_start = SyncA[2] ^ SyncA[1];
	assign TaskB_busy = TaskB_start | Busyhold; 

	always @(posedge clkB) Busyhold <= ~TaskB_done & TaskB_busy;
	always @(posedge clkB) 
		if(TaskB_busy & TaskB_done) FlagToggleB <= FlagToggleA;

	always @(posedge clkA) SyncB <= {SyncB[1:0], FlagToggleB};
	assign TaskA_busy = FlagToggleA ^ SyncB[2];
	assign TaskA_done = SyncB[2] ^ SyncB[1];

endmodule

bentch/TaskAck_CrossDomain_test.v
`include "../rtl/TaskAck_CrossDomain.v"
`timescale 1ns/100ps

module TaskAck_CrossDomain_test();

	reg clkA;
	reg clkB;
	reg TaskA_start;
	wire TaskA_busy;
	wire TaskA_done;
	wire TaskB_start;
	wire TaskB_busy;
	reg TaskB_done;

	
	initial clkA = 0;
	initial clkB = 0;
	initial TaskA_start = 0;
	initial TaskB_done = 0;

	always #20 clkA = !clkA;
	always #10 clkB = !clkB;


	TaskAck_CrossDomain i_tc(
		.clkA(clkA),
		.clkB(clkB),
		.TaskA_start(TaskA_start),
		.TaskA_busy(TaskA_busy),
		.TaskA_done(TaskA_done),
		.TaskB_start(TaskB_start),
		.TaskB_busy(TaskB_busy),
		.TaskB_done(TaskB_done)
	);

	initial begin

		#100;
		@(negedge clkA) TaskA_start = 1;
		@(negedge clkA) TaskA_start = 0;
		wait(TaskB_start)
		#100;
		@(negedge clkB) TaskB_done = 1;
		@(negedge clkB) TaskB_done = 0;
		#300 $finish;
	end

	initial begin
		//$monitor("%d, %b, %b, %b, %b, %b",$stime,clkA, clkB, FlagIn,FlagOut,my_Flag_CrossDomain.FlagToggle);
		$dumpfile("TaskAck_CrossDomain_test.vcd");
		//$dumpvars(0,Flag_CrossDomain_test);
		$dumpvars;
	end
endmodule

bentch/TaskAck_CrossDomain_test.vcd
$date
	Tue Nov  6 14:28:03 2018
$end
$version
	Icarus Verilog
$end
$timescale
	100ps
$end
$scope module TaskAck_CrossDomain_test $end
$var wire 1 ! TaskA_busy $end
$var wire 1 " TaskA_done $end
$var wire 1 # TaskB_busy $end
$var wire 1 $ TaskB_start $end
$var reg 1 % TaskA_start $end
$var reg 1 & TaskB_done $end
$var reg 1 ' clkA $end
$var reg 1 ( clkB $end
$scope module i_tc $end
$var wire 1 ! TaskA_busy $end
$var wire 1 " TaskA_done $end
$var wire 1 ) TaskA_start $end
$var wire 1 # TaskB_busy $end
$var wire 1 * TaskB_done $end
$var wire 1 $ TaskB_start $end
$var wire 1 + clkA $end
$var wire 1 , clkB $end
$var reg 1 - Busyhold $end
$var reg 1 . FlagToggleA $end
$var reg 1 / FlagToggleB $end
$var reg 3 0 SyncA [2:0] $end
$var reg 3 1 SyncB [2:0] $end
$upscope $end
$upscope $end
$enddefinitions $end
#0
$dumpvars
b0 1
b0 0
0/
0.
0-
0,
0+
0*
0)
0(
0'
0&
0%
0$
0#
0"
0!
$end
#100
1(
1,
#200
0(
0,
1'
1+
#300
1(
1,
#400
0(
0,
0'
0+
#500
1(
1,
#600
0(
0,
1'
1+
#700
1(
1,
#800
0(
0,
0'
0+
#900
1(
1,
#1000
0(
0,
1'
1+
#1100
1(
1,
#1200
1%
1)
0(
0,
0'
0+
#1300
1(
1,
#1400
1!
1.
0(
0,
1'
1+
#1500
b1 0
1(
1,
#1600
0%
0)
0(
0,
0'
0+
#1700
1#
1$
b11 0
1(
1,
#1800
0(
0,
1'
1+
#1900
0$
1-
b111 0
1(
1,
#2000
0(
0,
0'
0+
#2100
1(
1,
#2200
0(
0,
1'
1+
#2300
1(
1,
#2400
0(
0,
0'
0+
#2500
1(
1,
#2600
0(
0,
1'
1+
#2700
1(
1,
#2800
1&
1*
0(
0,
0'
0+
#2900
0#
0-
1/
1(
1,
#3000
b1 1
0&
0*
0(
0,
1'
1+
#3100
1(
1,
#3200
0(
0,
0'
0+
#3300
1(
1,
#3400
1"
b11 1
0(
0,
1'
1+
#3500
1(
1,
#3600
0(
0,
0'
0+
#3700
1(
1,
#3800
0!
0"
b111 1
0(
0,
1'
1+
